firewheel_repo_utilities/__init__.py
firewheel_repo_utilities/analytics/.gitignore
firewheel_repo_utilities/analytics/MANIFEST
firewheel_repo_utilities/analytics/README.rst
firewheel_repo_utilities/analytics/model_component_objects.py
firewheel_repo_utilities/analytics/INSTALL/tasks.yml
firewheel_repo_utilities/analytics/INSTALL/vars.yml
firewheel_repo_utilities/analytics/vm_resources/analytics.port_tracking.py
firewheel_repo_utilities/analytics/vm_resources/analytics.strace.py
firewheel_repo_utilities/analytics/vm_resources/analytics.tailf_dir.sh
firewheel_repo_utilities/analytics/vm_resources/kill_analytics.py
firewheel_repo_utilities/analytics/vm_resources/psutil.cpu_tracking.py
firewheel_repo_utilities/analytics/vm_resources/psutil.disk_io_tracking.py
firewheel_repo_utilities/analytics/vm_resources/psutil.disk_usage_tracking.py
firewheel_repo_utilities/analytics/vm_resources/psutil.network_io_tracking.py
firewheel_repo_utilities/analytics/vm_resources/psutil.system_memory_tracking.py
firewheel_repo_utilities/nodejs_vm/MANIFEST
firewheel_repo_utilities/nodejs_vm/README.rst
firewheel_repo_utilities/nodejs_vm/model_component_objects.py
firewheel_repo_utilities/nodejs_vm/INSTALL/tasks.yml
firewheel_repo_utilities/nodejs_vm/INSTALL/vars.yml
firewheel_repo_utilities/nodejs_vm/vm_resources/.gitkeep
firewheel_repo_utilities/python_vm/MANIFEST
firewheel_repo_utilities/python_vm/README.rst
firewheel_repo_utilities/python_vm/model_component_objects.py
firewheel_repo_utilities/python_vm/INSTALL/tasks.yml
firewheel_repo_utilities/python_vm/INSTALL/vars.yml
firewheel_repo_utilities/python_vm/vm_resources/.gitattributes
firewheel_repo_utilities/python_vm/vm_resources/install_pip_package.py
firewheel_repo_utilities/python_vm/vm_resources/pip_packages/.gitkeep
firewheel_repo_utilities/tools/.gitignore
firewheel_repo_utilities/tools/MANIFEST
firewheel_repo_utilities/tools/README.rst
firewheel_repo_utilities/tools/model_component_objects.py
firewheel_repo_utilities-1.1.0.dist-info/licenses/LICENSE
firewheel_repo_utilities-1.1.0.dist-info/METADATA
firewheel_repo_utilities-1.1.0.dist-info/WHEEL
firewheel_repo_utilities-1.1.0.dist-info/entry_points.txt
firewheel_repo_utilities-1.1.0.dist-info/top_level.txt
firewheel_repo_utilities-1.1.0.dist-info/RECORD
